fw_gear_oct_qa/__init__.py
fw_gear_oct_qa/calc_QA.py
fw_gear_oct_qa/format_qc.py
fw_gear_oct_qa/main.py
fw_gear_oct_qa/oct_qa.py
fw_gear_oct_qa/parser.py
fw_gear_oct_qa/utils/__init__.py
fw_gear_oct_qa/utils/docs.py
fw_gear_oct_qa-0.0.1.dev0.dist-info/LICENSE
fw_gear_oct_qa-0.0.1.dev0.dist-info/WHEEL
fw_gear_oct_qa-0.0.1.dev0.dist-info/METADATA
fw_gear_oct_qa-0.0.1.dev0.dist-info/RECORD
