Metadata-Version: 2.1
Name: fw-gear-oct-qa
Version: 0.0.1.dev0
Summary: OCT Quality Assessment
Home-page: https://gitlab.com/flywheel-io/flywheel-apps/oct-qa
License: MIT
Keywords: Flywheel,Gears
Author: Flywheel
Author-email: support@flywheel.io
Requires-Python: >=3.8,<4.0
Classifier: License :: OSI Approved :: MIT License
Classifier: Programming Language :: Python :: 3
Classifier: Programming Language :: Python :: 3.10
Classifier: Programming Language :: Python :: 3.8
Classifier: Programming Language :: Python :: 3.9
Classifier: Topic :: Scientific/Engineering
Requires-Dist: flywheel-gear-toolkit (>=0.6.5,<0.7.0)
Requires-Dist: fw-file[all] (>=1.0,<2.0)
Requires-Dist: matplotlib (>=3.4.2,<4.0.0)
Requires-Dist: numpy (>=1.21.1,<2.0.0)
Requires-Dist: opencv-python (>=4.5.3,<5.0.0)
Requires-Dist: pandas (>=1.3.1,<2.0.0)
Requires-Dist: pre-commit (>=2.13.0,<3.0.0)
Requires-Dist: regex (>=2021.8.3,<2022.0.0)
Requires-Dist: scipy (>=1.7.0,<2.0.0); python_version >= "3.8" and python_version < "3.10"
Project-URL: Repository, https://gitlab.com/flywheel-io/flywheel-apps/oct-qa
